{
  "version": 102,
  "id": "oil_slick",
  "name": "Oil Slick",
  "description": "A mysterious theme inspired by oil slick colors with iridescent blacks, deep purples, and rainbow highlights. Features shifting color patterns that mimic the mesmerizing rainbow sheen of oil on water.",
  "imageUrl": "/dark/oil_slick.png",
  "colors": {
    "node_slot": {
      "CLIP": "#9966cc",
      "CLIP_VISION": "#00ccff",
      "CLIP_VISION_OUTPUT": "#cc33ff",
      "CONDITIONING": "#ff66cc",
      "CONTROL_NET": "#3366ff",
      "IMAGE": "#00ffcc",
      "INT": "#9966cc",
      "LATENT": "#cc33ff",
      "MASK": "#00ccff",
      "MODEL": "#9966cc",
      "PIPE_LINE": "#ff66cc",
      "PIPE_LINE_SDXL": "#3366ff",
      "STYLE_MODEL": "#9966cc",
      "TAESD": "#00ffcc",
      "VAE": "#cc33ff",
      "XYPLOT": "#00ccff",
      "X_Y": "#ff66cc"
    },
    "litegraph_base": {
      "BACKGROUND_IMAGE": "",
      "CLEAR_BACKGROUND_COLOR": "#080808",
      "NODE_TITLE_COLOR": "#e0e0e0",
      "NODE_SELECTED_TITLE_COLOR": "#00ffcc",
      "NODE_TEXT_SIZE": 14,
      "NODE_TEXT_COLOR": "#e0e0e0",
      "NODE_TEXT_HIGHLIGHT_COLOR": "#ff66cc",
      "NODE_SUBTEXT_SIZE": 12,
      "NODE_DEFAULT_COLOR": "rgba(24, 24, 30, 0.85)",
      "NODE_DEFAULT_BGCOLOR": "rgba(8, 8, 12, 0.95)",
      "NODE_DEFAULT_BOXCOLOR": "#1a1a20",
      "NODE_DEFAULT_SHAPE": "box",
      "NODE_BOX_OUTLINE_COLOR": "#9966cc",
      "NODE_BYPASS_BGCOLOR": "#1a1a20",
      "NODE_ERROR_COLOUR": "#ff3366",
      "DEFAULT_SHADOW_COLOR": "rgba(153, 102, 204, 0.3)",
      "DEFAULT_GROUP_FONT": 24,
      "WIDGET_BGCOLOR": "#1a1a20",
      "WIDGET_OUTLINE_COLOR": "#3a3a45",
      "WIDGET_TEXT_COLOR": "#e0e0e0",
      "WIDGET_SECONDARY_TEXT_COLOR": "#cc33ff",
      "LINK_COLOR": "#00ccff",
      "EVENT_LINK_COLOR": "#ff66cc",
      "CONNECTING_LINK_COLOR": "#00ffcc",
      "BADGE_FG_COLOR": "#080808",
      "BADGE_BG_COLOR": "#9966cc"
    },
    "comfy_base": {
      "fg-color": "#e0e0e0",
      "bg-color": "#080808",
      "comfy-menu-bg": "rgba(8, 8, 12, 0.97)",
      "comfy-menu-hover-bg": "rgba(24, 24, 30, 0.97)",
      "comfy-menu-secondary-bg": "rgba(16, 16, 21, 0.97)",
      "comfy-input-bg": "#1a1a20",
      "input-text": "#e0e0e0",
      "descrip-text": "#9966cc",
      "drag-text": "#cc33ff",
      "error-text": "#ff3366",
      "border-color": "#3a3a45",
      "tr-even-bg-color": "rgba(24, 24, 30, 0.97)",
      "tr-odd-bg-color": "rgba(8, 8, 12, 0.97)",
      "content-bg": "#080808",
      "content-fg": "#e0e0e0",
      "content-hover-bg": "#1a1a20",
      "content-hover-fg": "#00ffcc",
      "bar-shadow": "rgba(153, 102, 204, 0.4) 0 0 12px"
    }
  }
}
